schutil/__init__.py
schutil/schutil.py
schutil-0.0.4.dist-info/METADATA
schutil-0.0.4.dist-info/WHEEL
schutil-0.0.4.dist-info/top_level.txt
schutil-0.0.4.dist-info/RECORD
