Metadata-Version: 2.4
Name: schutil
Version: 0.0.4
Summary: A collection of utility functions
Author: schuh
Author-email: schuh@schuh.wtf
License: MIT
Classifier: Programming Language :: Python :: 3
Classifier: License :: OSI Approved :: MIT License
Classifier: Operating System :: OS Independent
Requires-Python: >=3.7
